odoo/addons/product_sale_manufactured_for/README.rst
odoo/addons/product_sale_manufactured_for/__init__.py
odoo/addons/product_sale_manufactured_for/__manifest__.py
odoo/addons/product_sale_manufactured_for/i18n/es.po
odoo/addons/product_sale_manufactured_for/i18n/it.po
odoo/addons/product_sale_manufactured_for/i18n/nl.po
odoo/addons/product_sale_manufactured_for/i18n/nl_NL.po
odoo/addons/product_sale_manufactured_for/i18n/product_sale_manufactured_for.pot
odoo/addons/product_sale_manufactured_for/models/__init__.py
odoo/addons/product_sale_manufactured_for/models/product_product.py
odoo/addons/product_sale_manufactured_for/readme/CONTRIBUTORS.md
odoo/addons/product_sale_manufactured_for/readme/CREDITS.md
odoo/addons/product_sale_manufactured_for/readme/DESCRIPTION.md
odoo/addons/product_sale_manufactured_for/static/description/icon.png
odoo/addons/product_sale_manufactured_for/static/description/index.html
odoo/addons/product_sale_manufactured_for/views/product_product.xml
odoo/addons/product_sale_manufactured_for/views/sale_order.xml
odoo_addon_product_sale_manufactured_for-18.0.1.0.0.7.dist-info/METADATA
odoo_addon_product_sale_manufactured_for-18.0.1.0.0.7.dist-info/WHEEL
odoo_addon_product_sale_manufactured_for-18.0.1.0.0.7.dist-info/top_level.txt
odoo_addon_product_sale_manufactured_for-18.0.1.0.0.7.dist-info/RECORD
