Metadata-Version: 2.1
Name: odoo-addon-product_sale_manufactured_for
Version: 18.0.1.0.0.7
Requires-Python: >=3.10
Requires-Dist: odoo-addon-sale_commercial_partner==18.0.*
Requires-Dist: odoo==18.0.*
Summary: Allows to indicate in products that they were made specifically for some customers.
Home-page: https://github.com/OCA/product-attribute
License: AGPL-3
Author: Camptocamp, Odoo Community Association (OCA)
Author-email: support@odoo-community.org
Classifier: Programming Language :: Python
Classifier: Framework :: Odoo
Classifier: Framework :: Odoo :: 18.0
Classifier: License :: OSI Approved :: GNU Affero General Public License v3
